ontodocs/VERSION.py
ontodocs/__init__.py
ontodocs/main.py
ontodocs/core/CONFIG.py
ontodocs/core/__init__.py
ontodocs/core/builder.py
ontodocs/core/utils.py
ontodocs/core/viz_factory.py
ontodocs/media/static/custom/css/familytree.css
ontodocs/media/static/custom/css/simple-sidebar.css
ontodocs/media/static/custom/css/sticky-footer-navbar.css
ontodocs/media/static/custom/css/tabletree.css
ontodocs/media/static/custom/css/xxx_familytree.css
ontodocs/media/static/img/404-error.png
ontodocs/media/static/img/screenshot-basic-html.png
ontodocs/media/static/libs/bootstrap-3_3_7-dist/css/bootstrap-theme.css
ontodocs/media/static/libs/bootstrap-3_3_7-dist/css/bootstrap-theme.css.map
ontodocs/media/static/libs/bootstrap-3_3_7-dist/css/bootstrap-theme.min.css
ontodocs/media/static/libs/bootstrap-3_3_7-dist/css/bootstrap-theme.min.css.map
ontodocs/media/static/libs/bootstrap-3_3_7-dist/css/bootstrap.css
ontodocs/media/static/libs/bootstrap-3_3_7-dist/css/bootstrap.css.map
ontodocs/media/static/libs/bootstrap-3_3_7-dist/css/bootstrap.min.css
ontodocs/media/static/libs/bootstrap-3_3_7-dist/css/bootstrap.min.css.map
ontodocs/media/static/libs/bootstrap-3_3_7-dist/css/ie10-viewport-bug-workaround.css
ontodocs/media/static/libs/bootstrap-3_3_7-dist/fonts/glyphicons-halflings-regular.eot
ontodocs/media/static/libs/bootstrap-3_3_7-dist/fonts/glyphicons-halflings-regular.svg
ontodocs/media/static/libs/bootstrap-3_3_7-dist/fonts/glyphicons-halflings-regular.ttf
ontodocs/media/static/libs/bootstrap-3_3_7-dist/fonts/glyphicons-halflings-regular.woff
ontodocs/media/static/libs/bootstrap-3_3_7-dist/fonts/glyphicons-halflings-regular.woff2
ontodocs/media/static/libs/bootstrap-3_3_7-dist/js/bootstrap.js
ontodocs/media/static/libs/bootstrap-3_3_7-dist/js/bootstrap.min.js
ontodocs/media/static/libs/bootstrap-3_3_7-dist/js/ie10-viewport-bug-workaround.js
ontodocs/media/static/libs/bootstrap-3_3_7-dist/js/npm.js
ontodocs/media/static/libs/bootswatch3_2/cerulean/_bootswatch.scss
ontodocs-1.2.2.dist-info/LICENSE
ontodocs-1.2.2.dist-info/METADATA
ontodocs-1.2.2.dist-info/WHEEL
ontodocs-1.2.2.dist-info/entry_points.txt
ontodocs-1.2.2.dist-info/top_level.txt
ontodocs-1.2.2.dist-info/RECORD
