Metadata-Version: 2.1
Name: ontodocs
Version: 1.2.2
Summary: A Python package for creating ontology documentation
Home-page: https://github.com/lambdamusic/ontodocs
Author: Michele Pasin
Author-email: michele.pasin@gmail.com
License: MIT
Keywords: ontology semantic web linked data rdf owl documentation
Platform: UNKNOWN
Classifier: Development Status :: 4 - Beta
Classifier: Intended Audience :: Science/Research
Classifier: Intended Audience :: Developers
Classifier: Topic :: Scientific/Engineering :: Artificial Intelligence
Classifier: License :: OSI Approved :: MIT License
Classifier: Programming Language :: Python :: 2
Classifier: Programming Language :: Python :: 2.7
Classifier: Programming Language :: Python :: 3
Classifier: Programming Language :: Python :: 3.2
Classifier: Programming Language :: Python :: 3.3
Classifier: Programming Language :: Python :: 3.4
Requires-Dist: ontospy
Requires-Dist: django
Requires-Dist: pygments
